pydmd/__init__.py
pydmd/bopdmd.py
pydmd/cdmd.py
pydmd/costs.py
pydmd/dmd.py
pydmd/dmd_modes_tuner.py
pydmd/dmdbase.py
pydmd/dmdc.py
pydmd/dmdoperator.py
pydmd/edmd.py
pydmd/fbdmd.py
pydmd/hankeldmd.py
pydmd/havok.py
pydmd/hodmd.py
pydmd/lando.py
pydmd/mrcosts.py
pydmd/mrdmd.py
pydmd/optdmd.py
pydmd/paramdmd.py
pydmd/pidmd.py
pydmd/pidmd_utils.py
pydmd/plotter.py
pydmd/rdmd.py
pydmd/snapshots.py
pydmd/spdmd.py
pydmd/subspacedmd.py
pydmd/utils.py
pydmd/varprodmd.py
pydmd/preprocessing/__init__.py
pydmd/preprocessing/hankel.py
pydmd/preprocessing/pre_post_processing.py
pydmd/preprocessing/randomized.py
pydmd/preprocessing/svd_projection.py
pydmd/preprocessing/zero_mean.py
pydmd-2025.8.1.dist-info/LICENSE
pydmd-2025.8.1.dist-info/METADATA
pydmd-2025.8.1.dist-info/WHEEL
pydmd-2025.8.1.dist-info/top_level.txt
pydmd-2025.8.1.dist-info/RECORD
