Metadata-Version: 2.1
Name: PyDMD
Version: 2025.8.1
Summary: Python Dynamic Mode Decomposition.
Author: Nicola Demo, Marco Tezzele, Francesco Andreuzzi, Sara Ichinaga, Karl Lapo
Maintainer-email: pydmd.info@gmail.com
License: The MIT License (MIT)
Project-URL: Homepage, https://pydmd.github.io/PyDMD
Project-URL: Documentation, https://pydmd.github.io/PyDMD/code.html
Project-URL: Issues, https://github.com/PyDMD/PyDMD/issues
Project-URL: Repository, https://github.com/PyDMD/PyDMD
Keywords: dynamic-mode-decomposition,dmd
Classifier: Development Status :: 5 - Production/Stable
Classifier: License :: OSI Approved :: MIT License
Classifier: Programming Language :: Python :: 3
Classifier: Programming Language :: Python :: 3.8
Classifier: Programming Language :: Python :: 3.9
Classifier: Programming Language :: Python :: 3.10
Classifier: Programming Language :: Python :: 3.11
Classifier: Programming Language :: Python :: 3.12
Classifier: Intended Audience :: Science/Research
Classifier: Topic :: Scientific/Engineering :: Mathematics
Requires-Python: >=3.8
License-File: LICENSE
Requires-Dist: numpy
Requires-Dist: scipy>=1.6.0
Requires-Dist: matplotlib
Requires-Dist: scikit-learn
Requires-Dist: xarray
Requires-Dist: h5netcdf
Requires-Dist: typing-extensions>=4.7.0; python_version < "3.12"
Provides-Extra: docs
Requires-Dist: sphinx>=1.4; extra == "docs"
Requires-Dist: sphinx-rtd-theme; extra == "docs"
Provides-Extra: test
Requires-Dist: pytest; extra == "test"
Requires-Dist: pytest-cov; extra == "test"
Requires-Dist: pytest-mock; extra == "test"
Requires-Dist: ezyrb>=v1.2.1.post2205; extra == "test"
Provides-Extra: tutorial
Requires-Dist: jupyter; extra == "tutorial"
Requires-Dist: pandas; extra == "tutorial"
Requires-Dist: ezyrb; extra == "tutorial"
Requires-Dist: opencv-python; extra == "tutorial"
Requires-Dist: ffmpeg-python; extra == "tutorial"
